{
  "generated_at": "2026-04-15",
  "backtest_start": "2025-10-17",
  "backtest_end": "2026-04-15",
  "budget_per_trade_usd": 300.0,
  "hard_cost_ceiling_usd": 600.0,
  "sizing_policy": {
    "base_budget_per_trade_usd": 300.0,
    "hard_cost_ceiling_usd": 600.0,
    "allocation_weight_range": [
      0.25,
      3.0
    ],
    "confidence_scale_range": [
      0.2,
      1.0
    ],
    "skip_when_underfunded": true,
    "max_observed_cost_basis_usd": 0.0
  },
  "total_trades": 0,
  "winners": 0,
  "losers": 0,
  "expired_worthless": 0,
  "win_rate": 0.0,
  "avg_winner_pct": 0.0,
  "avg_loser_pct": 0.0,
  "total_pnl": 0.0,
  "total_deployed": 0.0,
  "net_return_pct": 0.0,
  "sharpe_ratio": 0.0,
  "max_drawdown": 0.0,
  "options_data_coverage": {
    "avg_options_data_coverage_pct": 0.0,
    "entry_real_trade_pct": 0.0,
    "exit_real_trade_pct": 0.0,
    "fully_real_trade_pct": 0.0,
    "entry_source_counts": {},
    "exit_source_counts": {}
  },
  "equity_curve": [],
  "side_breakdown": [],
  "symbol_breakdown": [],
  "best_trades": [],
  "worst_trades": [],
  "all_trades": [],
  "coverage_policy": {
    "strict_options_data": true,
    "min_real_coverage_pct": 1.0,
    "coverage_failed": true
  }
}