{
  "generated_at_utc": "2026-04-02T00:42:03+00:00",
  "product": "Orographic",
  "regime": {
    "mode": "risk_off",
    "bias": -0.2937,
    "source_symbol": "SPY",
    "notes": []
  },
  "scout_signals": [
    {
      "symbol": "META",
      "direction": "put",
      "spot": 579.23,
      "momentum_5d": -0.0263,
      "momentum_20d": -0.1325,
      "rsi_14": 36.49,
      "realized_vol_20d": 0.4746,
      "atr_pct_14d": 0.0363,
      "technical_score": -1.0,
      "empirical_score": -0.5161,
      "scout_score": -0.6651,
      "notes": []
    },
    {
      "symbol": "MSFT",
      "direction": "put",
      "spot": 369.37,
      "momentum_5d": -0.0045,
      "momentum_20d": -0.0884,
      "rsi_14": 26.91,
      "realized_vol_20d": 0.2197,
      "atr_pct_14d": 0.0228,
      "technical_score": -1.0,
      "empirical_score": -0.2855,
      "scout_score": -0.5914,
      "notes": []
    },
    {
      "symbol": "TSLA",
      "direction": "put",
      "spot": 381.26,
      "momentum_5d": -0.0122,
      "momentum_20d": -0.0608,
      "rsi_14": 44.17,
      "realized_vol_20d": 0.3805,
      "atr_pct_14d": 0.0344,
      "technical_score": -0.5291,
      "empirical_score": -0.2371,
      "scout_score": -0.3027,
      "notes": [
        "RSI is balanced, not yet extreme"
      ]
    },
    {
      "symbol": "NVDA",
      "direction": "put",
      "spot": 175.75,
      "momentum_5d": -0.0164,
      "momentum_20d": -0.0398,
      "rsi_14": 42.19,
      "realized_vol_20d": 0.3661,
      "atr_pct_14d": 0.031,
      "technical_score": -0.5013,
      "empirical_score": -0.1933,
      "scout_score": -0.2726,
      "notes": [
        "RSI is balanced, not yet extreme"
      ]
    },
    {
      "symbol": "QQQ",
      "direction": "put",
      "spot": 584.31,
      "momentum_5d": -0.006,
      "momentum_20d": -0.0433,
      "rsi_14": 43.76,
      "realized_vol_20d": 0.226,
      "atr_pct_14d": 0.019,
      "technical_score": -0.408,
      "empirical_score": -0.1567,
      "scout_score": -0.2068,
      "notes": [
        "RSI is balanced, not yet extreme"
      ]
    },
    {
      "symbol": "SPY",
      "direction": "put",
      "spot": 655.24,
      "momentum_5d": -0.0024,
      "momentum_20d": -0.0436,
      "rsi_14": 44.32,
      "realized_vol_20d": 0.1903,
      "atr_pct_14d": 0.0164,
      "technical_score": -0.3713,
      "empirical_score": -0.1417,
      "scout_score": -0.1807,
      "notes": [
        "RSI is balanced, not yet extreme"
      ]
    },
    {
      "symbol": "IWM",
      "direction": "put",
      "spot": 249.56,
      "momentum_5d": -0.009,
      "momentum_20d": -0.0466,
      "rsi_14": 52.28,
      "realized_vol_20d": 0.2575,
      "atr_pct_14d": 0.0232,
      "technical_score": -0.2411,
      "empirical_score": -0.1802,
      "scout_score": -0.1175,
      "notes": [
        "RSI is balanced, not yet extreme"
      ]
    },
    {
      "symbol": "AMD",
      "direction": "call",
      "spot": 210.21,
      "momentum_5d": -0.0457,
      "momentum_20d": 0.0403,
      "rsi_14": 57.99,
      "realized_vol_20d": 0.5425,
      "atr_pct_14d": 0.0455,
      "technical_score": 0.0734,
      "empirical_score": -0.0857,
      "scout_score": -0.0648,
      "notes": [
        "short-term momentum is strong",
        "RSI is balanced, not yet extreme"
      ]
    }
  ],
  "forge_candidates": [
    {
      "symbol": "NVDA",
      "contract_symbol": "NVDA260406P00172500",
      "option_type": "put",
      "expiry": "2026-04-06",
      "strike": 172.5,
      "bid": 1.16,
      "ask": 1.18,
      "last": 1.17,
      "premium": 1.18,
      "contract_cost": 118.0,
      "spread_pct": 0.0171,
      "open_interest": 2662,
      "volume": 4676,
      "implied_volatility": 0.3042,
      "delta": -0.2886,
      "moneyness": 0.0185,
      "projected_move_pct": 0.062,
      "breakeven_move_pct": 0.0252,
      "expected_return_pct": 5.481,
      "extrinsic_ratio": 1.0,
      "scout_score": -0.2726,
      "forge_score": 0.5743,
      "notes": [
        "projected payoff is asymmetric",
        "delta sits in the preferred weekly range"
      ]
    },
    {
      "symbol": "NVDA",
      "contract_symbol": "NVDA260406P00170000",
      "option_type": "put",
      "expiry": "2026-04-06",
      "strike": 170.0,
      "bid": 0.69,
      "ask": 0.7,
      "last": 0.7,
      "premium": 0.7,
      "contract_cost": 70.0,
      "spread_pct": 0.0144,
      "open_interest": 5063,
      "volume": 4642,
      "implied_volatility": 0.3267,
      "delta": -0.1831,
      "moneyness": 0.0327,
      "projected_move_pct": 0.062,
      "breakeven_move_pct": 0.0367,
      "expected_return_pct": 6.3536,
      "extrinsic_ratio": 1.0,
      "scout_score": -0.2726,
      "forge_score": 0.5673,
      "notes": [
        "projected payoff is asymmetric"
      ]
    },
    {
      "symbol": "MSFT",
      "contract_symbol": "MSFT260406P00360000",
      "option_type": "put",
      "expiry": "2026-04-06",
      "strike": 360.0,
      "bid": 1.17,
      "ask": 1.29,
      "last": 1.24,
      "premium": 1.29,
      "contract_cost": 129.0,
      "spread_pct": 0.0976,
      "open_interest": 521,
      "volume": 321,
      "implied_volatility": 0.2648,
      "delta": -0.1943,
      "moneyness": 0.0254,
      "projected_move_pct": 0.0717,
      "breakeven_move_pct": 0.0289,
      "expected_return_pct": 12.2677,
      "extrinsic_ratio": 1.0,
      "scout_score": -0.5914,
      "forge_score": 0.4413,
      "notes": [
        "projected payoff is asymmetric"
      ]
    }
  ],
  "council": {
    "live_board": [],
    "shadow_board": [
      {
        "symbol": "NVDA",
        "contract_symbol": "NVDA260406P00172500",
        "option_type": "put",
        "expiry": "2026-04-06",
        "strike": 172.5,
        "bid": 1.16,
        "ask": 1.18,
        "last": 1.17,
        "premium": 1.18,
        "contract_cost": 118.0,
        "spread_pct": 0.0171,
        "open_interest": 2662,
        "volume": 4676,
        "implied_volatility": 0.3042,
        "delta": -0.2886,
        "moneyness": 0.0185,
        "projected_move_pct": 0.062,
        "breakeven_move_pct": 0.0252,
        "expected_return_pct": 5.481,
        "extrinsic_ratio": 1.0,
        "scout_score": -0.2726,
        "forge_score": 0.5743,
        "notes": [
          "projected payoff is asymmetric",
          "delta sits in the preferred weekly range"
        ]
      },
      {
        "symbol": "NVDA",
        "contract_symbol": "NVDA260406P00170000",
        "option_type": "put",
        "expiry": "2026-04-06",
        "strike": 170.0,
        "bid": 0.69,
        "ask": 0.7,
        "last": 0.7,
        "premium": 0.7,
        "contract_cost": 70.0,
        "spread_pct": 0.0144,
        "open_interest": 5063,
        "volume": 4642,
        "implied_volatility": 0.3267,
        "delta": -0.1831,
        "moneyness": 0.0327,
        "projected_move_pct": 0.062,
        "breakeven_move_pct": 0.0367,
        "expected_return_pct": 6.3536,
        "extrinsic_ratio": 1.0,
        "scout_score": -0.2726,
        "forge_score": 0.5673,
        "notes": [
          "projected payoff is asymmetric"
        ]
      },
      {
        "symbol": "MSFT",
        "contract_symbol": "MSFT260406P00360000",
        "option_type": "put",
        "expiry": "2026-04-06",
        "strike": 360.0,
        "bid": 1.17,
        "ask": 1.29,
        "last": 1.24,
        "premium": 1.29,
        "contract_cost": 129.0,
        "spread_pct": 0.0976,
        "open_interest": 521,
        "volume": 321,
        "implied_volatility": 0.2648,
        "delta": -0.1943,
        "moneyness": 0.0254,
        "projected_move_pct": 0.0717,
        "breakeven_move_pct": 0.0289,
        "expected_return_pct": 12.2677,
        "extrinsic_ratio": 1.0,
        "scout_score": -0.5914,
        "forge_score": 0.4413,
        "notes": [
          "projected payoff is asymmetric"
        ]
      }
    ],
    "abstain": true,
    "summary": {
      "candidate_count": 3,
      "live_count": 0,
      "shadow_count": 3,
      "regime_mode": "risk_off",
      "minimum_live_score": 0.57,
      "notes": [
        "Council abstained because no contract cleared the live board threshold.",
        "Council is operating under a risk-off market regime."
      ]
    }
  },
  "summary": {
    "universe_size": 10,
    "scout_signal_count": 10,
    "forge_candidate_count": 3,
    "abstain": true,
    "live_avg_score": 0.0
  }
}